dry_scraper/__init__.py
dry_scraper/data_source.py
dry_scraper/nhl/__init__.py
dry_scraper/nhl/nhl_api_sources.py
dry_scraper/nhl/pydantic_models/base_model.py
dry_scraper/nhl/pydantic_models/nhl_conferences_api_source.py
dry_scraper/nhl/pydantic_models/nhl_divisions_api_source.py
dry_scraper/nhl/pydantic_models/nhl_game_content_api_source.py
dry_scraper/nhl/pydantic_models/nhl_game_live_feed_api_source.py
dry_scraper/nhl/pydantic_models/nhl_people_api_source.py
dry_scraper/nhl/pydantic_models/nhl_schedule_api_source.py
dry_scraper/nhl/pydantic_models/nhl_teams_api_source.py
dry_scraper/shared.py
dry_scraper/teams.py
dry_scraper-0.1.8.9.dist-info/LICENSE
dry_scraper-0.1.8.9.dist-info/METADATA
dry_scraper-0.1.8.9.dist-info/WHEEL
dry_scraper-0.1.8.9.dist-info/RECORD
