Metadata-Version: 2.1
Name: dry-scraper
Version: 0.1.8.9
Summary: A framework for retrieving and parsing hockey data into useful forms.
License: GNU General Public License v3.0
Author: cak
Author-email: chris@cak.co
Requires-Python: >=3.10,<4.0
Classifier: License :: Other/Proprietary License
Classifier: Programming Language :: Python :: 3
Classifier: Programming Language :: Python :: 3.10
Classifier: Programming Language :: Python :: 3.11
Requires-Dist: beautifulsoup4 (>=4.11.1,<5.0.0)
Requires-Dist: fastapi (>=0.99.0,<0.100.0)
Requires-Dist: pandas (>=2.0.3,<3.0.0)
Requires-Dist: pydantic (>=1.10.11,<2.0.0)
Requires-Dist: requests (>=2.28.1,<3.0.0)
Requires-Dist: sqlalchemy (>=2.0.18,<3.0.0)
Requires-Dist: uuid (>=1.30,<2.0)
